frrmvsm/__init__.py
frrmvsm/add.py
frrmvsm/divide.py
frrmvsm/frrmvsm.py
frrmvsm/multiply.py
frrmvsm/subtract.py
frrmvsm-0.0.9.dist-info/METADATA
frrmvsm-0.0.9.dist-info/WHEEL
frrmvsm-0.0.9.dist-info/entry_points.txt
frrmvsm-0.0.9.dist-info/top_level.txt
frrmvsm-0.0.9.dist-info/RECORD
